jsongeekai/__init__.py
jsongeekai/exceptions.py
jsongeekai/formats.py
jsongeekai/formats_ext.py
jsongeekai/parallel.py
jsongeekai/parser.py
jsongeekai/simd.py
jsongeekai/simd/__init__.py
jsongeekai/simd/avx2.py
jsongeekai/simd/base.py
jsongeekai/simd/factory.py
jsongeekai/simd/neon.py
jsongeekai-0.2.0.dist-info/LICENSE
jsongeekai-0.2.0.dist-info/METADATA
jsongeekai-0.2.0.dist-info/WHEEL
jsongeekai-0.2.0.dist-info/top_level.txt
jsongeekai-0.2.0.dist-info/RECORD
