Metadata-Version: 2.2
Name: jsongeekai
Version: 0.2.0
Summary: A high-performance JSON parser with AI-driven optimizations
Author-email: Zhang Hongping <zhanghongping@live.com>
License: MIT License
Project-URL: Homepage, https://github.com/zhanghongping/jsongeekai
Project-URL: Documentation, https://jsongeekai.readthedocs.io/
Project-URL: Repository, https://github.com/zhanghongping/jsongeekai.git
Project-URL: Changelog, https://github.com/zhanghongping/jsongeekai/blob/main/CHANGELOG.md
Requires-Python: >=3.8
License-File: LICENSE
Requires-Dist: numpy>=2.1.3
Requires-Dist: numba>=0.61.0
Requires-Dist: py-cpuinfo>=9.0.0
Requires-Dist: json5>=0.9.14
Requires-Dist: pyyaml>=6.0.1
Requires-Dist: msgpack>=1.0.7
Requires-Dist: psutil>=7.0.0
Requires-Dist: ijson>=3.3.0
Provides-Extra: test
Requires-Dist: pytest>=7.4.0; extra == "test"
Requires-Dist: pytest-benchmark>=4.0.0; extra == "test"
